signal_transformation/__init__.py
signal_transformation/helpers.py
signal_transformation/images/__init__.py
signal_transformation/images/bin/__init__.py
signal_transformation/tf/__init__.py
signal_transformation/torch/__init__.py
signal_transformation/torch/models/__init__.py
signal_transformation/torch/models/matchboxnet.py
signal_transformation/voice/SpectFormat.py
signal_transformation/voice/__init__.py
signal_transformation/voice/lrtr.py
signal_transformation/voice/tftr.py
signal_transformation/voice/vad.py
signal_transformation/voice/bin/__init__.py
signal_transformation-2.5.0.data/scripts/imagenet_to_tf_records
signal_transformation-2.5.0.data/scripts/vox_to_metadata
signal_transformation-2.5.0.data/scripts/wav_to_tf_records
signal_transformation-2.5.0.dist-info/LICENSE
signal_transformation-2.5.0.dist-info/METADATA
signal_transformation-2.5.0.dist-info/WHEEL
signal_transformation-2.5.0.dist-info/top_level.txt
signal_transformation-2.5.0.dist-info/RECORD
