Metadata-Version: 2.1
Name: signal-transformation
Version: 2.5.0
Summary: The package allows performing a transformation of a signal using TensorFlow, Pytorch or LibROSA
Home-page: https://github.com/Ilyushin/signal-transformation
Author: Eugene Ilyushin
Author-email: eugene.ilyushin@gmail.com
Classifier: Programming Language :: Python :: 3
Classifier: License :: OSI Approved :: MIT License
Classifier: Operating System :: OS Independent
License-File: LICENSE
Requires-Dist: numpy (==1.22.2)
Requires-Dist: pydub (==0.25.1)
Requires-Dist: pylint (==2.16.2)
Requires-Dist: librosa (==0.9.2)
Requires-Dist: ffmpeg (==1.4)
Requires-Dist: webrtcvad (==2.0.10)
Requires-Dist: setuptools (==65.6.3)
Requires-Dist: pandas (==1.5.3)
Requires-Dist: pyarrow (==11.0.0)
Requires-Dist: absl-py (==1.4.0)
Requires-Dist: torch (>=2.0.0)
Requires-Dist: tensorflow (==2.12.0) ; sys_platform != "darwin" or platform_machine != "arm64"
Requires-Dist: tensorflow-macos (==2.12.0) ; sys_platform == "darwin" and platform_machine == "arm64"
